hippy/__about__.py
hippy/__init__.py
hippy/compiler.py
hippy/error.py
hippy/lexer.py
hippy/parser.py
HipPy-0.0.0.dist-info/DESCRIPTION.rst
HipPy-0.0.0.dist-info/METADATA
HipPy-0.0.0.dist-info/metadata.json
HipPy-0.0.0.dist-info/RECORD
HipPy-0.0.0.dist-info/top_level.txt
HipPy-0.0.0.dist-info/WHEEL
