Metadata-Version: 2.0
Name: HipPy
Version: 0.0.0
Summary: A parser for the Hip data serialization format.
Home-page: https://github.com/Sean1708/HipPy
Author: Sean Marshallsay
Author-email: srm.1708@gmail.com
License: UNKNOWN
Download-URL: https://github.com/Sean1708/HipPy.git
Platform: UNKNOWN
